{
    "Ar36": {
        "error": 0.00032677984536467575,
        "error_type": "",
        "fit": "previous",
        "references": [
            {
                "exclude": false,
                "record_id": "ba-01-A-32223"
            }
        ],
        "value": 0.019615583286415373
    },
    "Ar37": {
        "error": 0.009294610631199643,
        "error_type": "",
        "fit": "previous",
        "references": [
            {
                "exclude": false,
                "record_id": "ba-01-A-32223"
            }
        ],
        "value": 0.0201196883124422
    },
    "Ar38": {
        "error": 0.01020209282126603,
        "error_type": "",
        "fit": "previous",
        "references": [
            {
                "exclude": false,
                "record_id": "ba-01-A-32223"
            }
        ],
        "value": 0.010136732041305297
    },
    "Ar39": {
        "error": 0.00873728168632154,
        "error_type": "",
        "fit": "previous",
        "references": [
            {
                "exclude": false,
                "record_id": "ba-01-A-32223"
            }
        ],
        "value": 0.0800837215055265
    },
    "Ar40": {
        "error": 0.021747304940718786,
        "error_type": "",
        "fit": "previous",
        "references": [
            {
                "exclude": false,
                "record_id": "ba-01-A-32223"
            }
        ],
        "value": 5.680332460311818
    }
}